memfactory/__init__.py
memfactory/main.py
memfactory-0.1.0.dist-info/licenses/LICENSE
memfactory-0.1.0.dist-info/METADATA
memfactory-0.1.0.dist-info/WHEEL
memfactory-0.1.0.dist-info/top_level.txt
memfactory-0.1.0.dist-info/RECORD
