Metadata-Version: 2.4
Name: memfactory
Version: 0.1.0
Summary: description for memfactory
Author-email: ziheng li <valsure@icloud.com>, ziliang guo <example@icloud.com>, zhiyu li <example@icloud.com>
Project-URL: Homepage, https://github.com
Classifier: Programming Language :: Python :: 3
Classifier: License :: OSI Approved :: MIT License
Classifier: Operating System :: OS Independent
Requires-Python: >=3.7
License-File: LICENSE
Dynamic: license-file
